<?xml version='1.0' encoding='utf-8'?>
<citationChunk xmlns:tei="http://www.tei-c.org/ns/1.0" unit="chapter" base_urn="urn:cts:greekLit:tlg0016.tlg001.perseus-grc2" cts_urn="urn:cts:greekLit:tlg0016.tlg001.perseus-grc2:3.115" prev_urn="urn:cts:greekLit:tlg0016.tlg001.perseus-grc2:3.114" next_urn="urn:cts:greekLit:tlg0016.tlg001.perseus-grc2:3.116">
  <elements><tei:div n="115" type="chapter">
               <tei:div n="1" type="section">
                  <tei:p rend="indent">αὗται μέν νυν ἔν τε τῇ Ἀσίῃ ἐσχατιαί εἰσι καὶ ἐν τῇ Λιβύῃ.  περὶ δὲ τῶν ἐν τῇ Εὐρώπῃ τῶν πρὸς ἑσπέρην ἐσχατιέων ἔχω μὲν οὐκ ἀτρεκέως λέγειν· οὔτε γὰρ ἔγωγε ἐνδέκομαι Ἠριδανὸν καλέεσθαι πρὸς βαρβάρων ποταμὸν ἐκδιδόντα ἐς θάλασσαν τὴν πρὸς βορέην ἄνεμον, ἀπʼ ὅτευ τὸ ἤλεκτρον φοιτᾶν λόγος ἐστί, οὔτε νήσους οἶδα Κασσιτερίδας ἐούσας, ἐκ τῶν ὁ κασσίτερος ἡμῖν φοιτᾷ.
</tei:p>
               </tei:div>
               <tei:div n="2" type="section">
                  <tei:p>
τοῦτο μὲν γὰρ ὁ Ἠριδανὸς αὐτὸ κατηγορέει τὸ οὔνομα ὡς ἔστι Ἑλληνικὸν καὶ οὐ βάρβαρον, ὑπὸ ποιητέω δὲ τινὸς ποιηθέν· τοῦτο δὲ οὐδενὸς αὐτόπτεω γενομένου δύναμαι ἀκοῦσαι, τοῦτο μελετῶν, ὅκως θάλασσα ἐστὶ τὰ ἐπέκεινα Εὐρώπης.  ἐξ ἐσχάτης δʼ ὦν ὁ κασσίτερος ἡμῖν φοιτᾷ καὶ τὸ ἤλεκτρον.

</tei:p>
               </tei:div>
            </tei:div>
            </elements>
</citationChunk>
