<?xml version='1.0' encoding='utf-8'?>
<citationChunk xmlns:tei="http://www.tei-c.org/ns/1.0" unit="chapter" base_urn="urn:cts:greekLit:tlg0016.tlg001.perseus-grc2" cts_urn="urn:cts:greekLit:tlg0016.tlg001.perseus-grc2:9.23" prev_urn="urn:cts:greekLit:tlg0016.tlg001.perseus-grc2:9.22" next_urn="urn:cts:greekLit:tlg0016.tlg001.perseus-grc2:9.24">
  <elements><tei:div n="23" type="chapter">
               <tei:div n="1" type="section">
                  <tei:p rend="indent">ἰδόντες δὲ οἱ Ἀθηναῖοι οὐκέτι κατὰ τέλεα προσελαύνοντας τοὺς ἱππέας ἀλλὰ πάντας, τὴν ἄλλην στρατιὴν ἐπεβώσαντο. ἐν ᾧ δὲ ὁ πεζὸς ἅπας ἐβοήθεε, ἐν τούτῳ μάχη ὀξέα περὶ τοῦ νεκροῦ γίνεται.
</tei:p>
               </tei:div>
               <tei:div n="2" type="section">
                  <tei:p>
ἕως μέν νυν μοῦνοι ἦσαν οἱ τριηκόσιοι, ἑσσοῦντό τε πολλὸν καὶ τὸν νεκρὸν ἀπέλειπον· ὡς δέ σφι τὸ πλῆθος ἐπεβοήθησε, οὕτω δὴ οὐκέτι οἱ ἱππόται ὑπέμενον οὐδέ σφι ἐξεγένετο τὸν νεκρὸν ἀνελέσθαι, ἀλλὰ πρὸς ἐκείνῳ ἄλλους προσαπώλεσαν τῶν ἱππέων. ἀποστήσαντες ὦν ὅσον τε δύο στάδια ἐβουλεύοντο ὅ τι χρεὸν εἴη ποιέειν· ἐδόκεε δέ σφι ἀναρχίης ἐούσης ἀπελαύνειν παρὰ Μαρδόνιον.

</tei:p>
               </tei:div>
            </tei:div>
            </elements>
</citationChunk>
