<?xml version='1.0' encoding='utf-8'?>
<citationChunk xmlns:tei="http://www.tei-c.org/ns/1.0" unit="scene" base_urn="urn:cts:greekLit:tlg0006.tlg018.perseus-grc2" cts_urn="urn:cts:greekLit:tlg0006.tlg018.perseus-grc2:801-1035" prev_urn="urn:cts:greekLit:tlg0006.tlg018.perseus-grc2:751-800" next_urn="urn:cts:greekLit:tlg0006.tlg018.perseus-grc2:1036-1097">
  <elements><tei:div type="episode">
            <tei:sp>
               <tei:speaker>Ἀχιλλεύς</tei:speaker>
               <tei:l rend="indent" n="801">ποῦ τῶν Ἀχαιῶν ἐνθάδʼ ὁ στρατηλάτης;</tei:l>
               <tei:l n="802">τίς ἂν φράσειε προσπόλων τὸν Πηλέως</tei:l>
               <tei:l n="803">ζητοῦντά νιν παῖδʼ ἐν πύλαις Ἀχιλλέα;</tei:l>
               <tei:l n="804">οὐκ ἐξ ἴσου γὰρ μένομεν Εὐρίπου πέλας.</tei:l>
               <tei:l n="805">οἳ μὲν γὰρ ἡμῶν, ὄντες ἄζυγες γάμων,</tei:l>
               <tei:l n="806">οἴκους ἐρήμους ἐκλιπόντες ἐνθάδε</tei:l>
               <tei:l n="807">θάσσουσʼ ἐπʼ ἀκταῖς, οἳ δʼ ἔχοντες εὔνιδας</tei:l>
               <tei:l n="808">ἄπαιδες· οὕτω δεινὸς ἐμπέπτωκʼ ἔρως</tei:l>
               <tei:l n="809">τῆσδε στρατείας Ἑλλάδʼ οὐκ ἄνευ θεῶν.</tei:l>
               <tei:l n="810">τοὐμὸν μὲν οὖν δίκαιον ἐμὲ λέγειν χρεών,</tei:l>
               <tei:l n="811">ἄλλος δʼ ὁ χρῄζων αὐτὸς ὑπὲρ αὑτοῦ φράσει.</tei:l>
               <tei:l n="812">γῆν γὰρ λιπὼν Φάρσαλον ἠδὲ Πηλέα</tei:l>
               <tei:l n="813">μένω ʼπὶ λεπταῖς ταισίδʼ Εὐρίπου πνοαῖς,</tei:l>
               <tei:l n="814">Μυρμιδόνας ἴσχων· οἳ δʼ ἀεὶ προσκείμενοι</tei:l>
               <tei:l n="815">λέγουσʼ· Ἀχιλλεῦ, τί μένομεν; πόσον χρόνον</tei:l>
               <tei:l n="816">ἔτʼ ἐκμετρῆσαι χρὴ πρὸς Ἰλίου στόλον;</tei:l>
               <tei:l n="817">δρᾶ γʼ, εἴ τι δράσεις, ἢ ἄπαγʼ οἴκαδε στρατόν,</tei:l>
               <tei:l n="818">τὰ τῶν Ἀτρειδῶν μὴ μένων μελλήματα.</tei:l>
            </tei:sp>
            <tei:sp>
               <tei:speaker>Κλυταιμήστρα</tei:speaker>
               <tei:l rend="indent" n="819">ὦ παῖ θεᾶς Νηρῇδος, ἔνδοθεν λόγων</tei:l>
               <tei:l n="820">τῶν σῶν ἀκούσασʼ ἐξέβην πρὸ δωμάτων.</tei:l>
            </tei:sp>
            <tei:sp>
               <tei:speaker>Ἀχιλλεύς</tei:speaker>
               <tei:l rend="indent" n="821">ὦ πότνιʼ αἰδώς, τήνδε τίνα λεύσσω ποτὲ</tei:l>
               <tei:l n="822">γυναῖκα, μορφὴν εὐπρεπῆ κεκτημένην;</tei:l>
            </tei:sp>
            <tei:sp>
               <tei:speaker>Κλυταιμήστρα</tei:speaker>
               <tei:l rend="indent" n="823">οὐ θαῦμά σʼ ἡμᾶς ἀγνοεῖν, οἷς μὴ πάρος</tei:l>
               <tei:l n="824">προσῆκες· αἰνῶ δʼ ὅτι σέβεις τὸ σωφρονεῖν.</tei:l>
            </tei:sp>
            <tei:sp>
               <tei:speaker>Ἀχιλλεύς</tei:speaker>
               <tei:l rend="indent" n="825">τίς δʼ εἶ; τί δʼ ἦλθες Δαναϊδῶν ἐς σύλλογον,</tei:l>
               <tei:l n="826">γυνὴ πρὸς ἄνδρας ἀσπίσιν πεφραγμένους;</tei:l>
            </tei:sp>
            <tei:sp>
               <tei:speaker>Κλυταιμήστρα</tei:speaker>
               <tei:l rend="indent" n="827">Λήδας μέν εἰμι παῖς, Κλυταιμήστρα δέ μοι</tei:l>
               <tei:l n="828">ὄνομα, πόσις δέ μοὐστὶν Ἀγαμέμνων ἄναξ.</tei:l>
            </tei:sp>
            <tei:sp>
               <tei:speaker>Ἀχιλλεύς</tei:speaker>
               <tei:l rend="indent" n="829">καλῶς ἔλεξας ἐν βραχεῖ τὰ καίρια.</tei:l>
               <tei:l n="830">αἰσχρὸν δέ μοι γυναιξὶ συμβάλλειν λόγους.</tei:l>
            </tei:sp>
            <tei:milestone resp="perseus" unit="card" n="831"/>
            <tei:sp>
               <tei:speaker>Κλυταιμήστρα</tei:speaker>
               <tei:l rend="indent" n="831">μεῖνον — τί φεύγεις; — δεξιάν τʼ ἐμῇ χερὶ</tei:l>
               <tei:l n="832">σύναψον, ἀρχὴν μακαρίαν νυμφευμάτων.</tei:l>
            </tei:sp>
            <tei:sp>
               <tei:speaker>Ἀχιλλεύς</tei:speaker>
               <tei:l rend="indent" n="833">τί φῄς; ἐγώ σοι δεξιάν; αἰδοίμεθʼ ἂν</tei:l>
               <tei:l n="834">Ἀγαμέμνονʼ, εἰ ψαύοιμεν ὧν μή μοι θέμις.</tei:l>
            </tei:sp>
            <tei:sp>
               <tei:speaker>Κλυταιμήστρα</tei:speaker>
               <tei:l rend="indent" n="835">θέμις μάλιστα, τὴν ἐμὴν ἐπεὶ γαμεῖς</tei:l>
               <tei:l n="836">παῖδʼ, ὦ θεᾶς παῖ ποντίας Νηρηίδος.</tei:l>
            </tei:sp>
            <tei:sp>
               <tei:speaker>Ἀχιλλεύς</tei:speaker>
               <tei:l rend="indent" n="837">ποίους γάμους φῄς; ἀφασία μʼ ἔχει, γύναι·</tei:l>
               <tei:l n="838">εἰ μή τι παρανοοῦσα καινουργεῖς λόγον;</tei:l>
            </tei:sp>
            <tei:sp>
               <tei:speaker>Κλυταιμήστρα</tei:speaker>
               <tei:l rend="indent" n="839">πᾶσιν τόδʼ ἐμπέφυκεν, αἰδεῖσθαι φίλους</tei:l>
               <tei:l n="840">καινοὺς ὁρῶσι καὶ γάμου μεμνημένοις.</tei:l>
            </tei:sp>
            <tei:sp>
               <tei:speaker>Ἀχιλλεύς</tei:speaker>
               <tei:l rend="indent" n="841">οὐπώποτʼ ἐμνήστευσα παῖδα σήν, γύναι,</tei:l>
               <tei:l n="842">οὐδʼ ἐξ Ἀτρειδῶν ἦλθέ μοι λόγος γάμων.</tei:l>
            </tei:sp>
            <tei:sp>
               <tei:speaker>Κλυταιμήστρα</tei:speaker>
               <tei:l rend="indent" n="843">τί δῆτʼ ἂν εἴη; σὺ πάλιν αὖ λόγους ἐμοὺς</tei:l>
               <tei:l n="844">θαύμαζʼ· ἐμοὶ γὰρ θαύματʼ ἐστὶ τὰ παρὰ σοῦ.</tei:l>
            </tei:sp>
            <tei:sp>
               <tei:speaker>Ἀχιλλεύς</tei:speaker>
               <tei:l rend="indent" n="845">εἴκαζε· κοινόν ἐστιν εἰκάζειν τάδε·</tei:l>
               <tei:l n="846">ἄμφω γὰρ οὐ ψευδόμεθα τοῖς λόγοις ἴσως.</tei:l>
            </tei:sp>
            <tei:sp>
               <tei:speaker>Κλυταιμήστρα</tei:speaker>
               <tei:l rend="indent" n="847">ἀλλʼ ἦ πέπονθα δεινά; μνηστεύω γάμους</tei:l>
               <tei:l n="848">οὐκ ὄντας, ὡς εἴξασιν· αἰδοῦμαι τάδε.</tei:l>
            </tei:sp>
            <tei:sp>
               <tei:speaker>Ἀχιλλεύς</tei:speaker>
               <tei:l rend="indent" n="849">ἴσως ἐκερτόμησε κἀμὲ καὶ σέ τις.</tei:l>
               <tei:l n="850">ἀλλʼ ἀμελίᾳ δὸς αὐτὰ καὶ φαύλως φέρε.</tei:l>
            </tei:sp>
            <tei:sp>
               <tei:speaker>Κλυταιμήστρα</tei:speaker>
               <tei:l rend="indent" n="851">χαῖρʼ· οὐ γὰρ ὀρθοῖς ὄμμασίν σʼ ἔτʼ εἰσορῶ,</tei:l>
               <tei:l n="852">ψευδὴς γενομένη καὶ παθοῦσʼ ἀνάξια.</tei:l>
            </tei:sp>
            <tei:sp>
               <tei:speaker>Ἀχιλλεύς</tei:speaker>
               <tei:l rend="indent" n="853">καὶ σοὶ τόδʼ ἐστὶν ἐξ ἐμοῦ· πόσιν δὲ σὸν</tei:l>
               <tei:l n="854">στείχω ματεύσων τῶνδε δωμάτων ἔσω.</tei:l>
            </tei:sp>
            <tei:milestone resp="perseus" unit="card" n="855"/>
            <tei:div type="trochees">
               <tei:sp>
                  <tei:speaker>Πρεσβύτης</tei:speaker>
                  <tei:l rend="indent" n="855">ὦ ξένʼ, Αἰακοῦ γένεθλον, μεῖνον· ὦ, σέ τοι λέγω,</tei:l>
                  <tei:l n="856">τὸν θεᾶς γεγῶτα παῖδα, καὶ σέ, τὴν Λήδας κόρην.</tei:l>
               </tei:sp>
               <tei:sp>
                  <tei:speaker>Ἀχιλλεύς</tei:speaker>
                  <tei:l rend="indent" n="857">τίς ὁ καλῶν πύλας παροίξας; ὡς τεταρβηκὼς καλεῖ.</tei:l>
               </tei:sp>
               <tei:sp>
                  <tei:speaker>Πρεσβύτης</tei:speaker>
                  <tei:l rend="indent" n="858">δοῦλος, οὐχ ἁβρύνομαι τῷδʼ· ἡ τύχη γὰρ οὐκ ἐᾷ.</tei:l>
               </tei:sp>
               <tei:sp>
                  <tei:speaker>Ἀχιλλεύς</tei:speaker>
                  <tei:l rend="indent" n="859">τίνος; ἐμὸς μὲν οὐχί· χωρὶς τἀμὰ καὶ Ἀγαμέμνονος.</tei:l>
               </tei:sp>
               <tei:sp>
                  <tei:speaker>Πρεσβύτης</tei:speaker>
                  <tei:l rend="indent" n="860">τῆσδε τῆς πάροιθεν οἴκων, Τυνδάρεω δόντος πατρός.</tei:l>
               </tei:sp>
               <tei:sp>
                  <tei:speaker>Ἀχιλλεύς</tei:speaker>
                  <tei:l rend="indent" n="861">ἕσταμεν· φράζʼ, εἴ τι χρῄζεις, ὧν μʼ ἐπέσχες οὕνεκα.</tei:l>
               </tei:sp>
               <tei:sp>
                  <tei:speaker>Πρεσβύτης</tei:speaker>
                  <tei:l rend="indent" n="862">ἦ μόνω παρόντε δῆτα ταῖσδʼ ἐφέστατον πύλαις;</tei:l>
               </tei:sp>
               <tei:sp>
                  <tei:speaker>Ἀχιλλεύς</tei:speaker>
                  <tei:l rend="indent" n="863">ὡς μόνοιν λέγοις ἄν, ἔξω δʼ ἐλθὲ βασιλείων δόμων.</tei:l>
               </tei:sp>
               <tei:sp>
                  <tei:speaker>Πρεσβύτης</tei:speaker>
                  <tei:l rend="indent" n="864">ὦ Τύχη πρόνοιά θʼ ἡμή, σῴσαθʼ οὓς ἐγὼ θέλω.</tei:l>
               </tei:sp>
               <tei:sp>
                  <tei:speaker>Ἀχιλλεύς</tei:speaker>
                  <tei:l rend="indent" n="865">ὁ λόγος ἐς μέλλοντʼ <tei:sic>ἂν ὤση</tei:sic> χρόνον· ἔχει δʼ
                     ὄγκον τινά.</tei:l>
               </tei:sp>
               <tei:sp>
                  <tei:speaker>Κλυταιμήστρα</tei:speaker>
                  <tei:l rend="indent" n="866">δεξιᾶς ἕκατι μὴ μέλλʼ, εἴ τί μοι χρῄζεις λέγειν.</tei:l>
               </tei:sp>
               <tei:sp>
                  <tei:speaker>Πρεσβύτης</tei:speaker>
                  <tei:l rend="indent" n="867">οἶσθα δῆτʼ ἔμʼ, ὅστις ὢν σοὶ καὶ τέκνοις εὔνους ἔφυν;</tei:l>
               </tei:sp>
               <tei:sp>
                  <tei:speaker>Κλυταιμήστρα</tei:speaker>
                  <tei:l rend="indent" n="868">οἶδά σʼ ὄντʼ ἐγὼ παλαιὸν δωμάτων ἐμῶν λάτριν.</tei:l>
               </tei:sp>
               <tei:sp>
                  <tei:speaker>Πρεσβύτης</tei:speaker>
                  <tei:l rend="indent" n="869">χὥτι μʼ ἐν ταῖς σαῖσι φερναῖς ἔλαβεν Ἀγαμέμνων ἄναξ;</tei:l>
               </tei:sp>
               <tei:sp>
                  <tei:speaker>Κλυταιμήστρα</tei:speaker>
                  <tei:l rend="indent" n="870">ἦλθες εἰς Ἄργος μεθʼ ἡμῶν καὶ ἐμὸς ἦσθʼ ἀεί ποτε.</tei:l>
               </tei:sp>
               <tei:sp>
                  <tei:speaker>Πρεσβύτης</tei:speaker>
                  <tei:l rend="indent" n="871">ὧδʼ ἔχει. καὶ σοὶ μὲν εὔνους εἰμί, σῷ δʼ ἧσσον πόσει.</tei:l>
               </tei:sp>
               <tei:sp>
                  <tei:speaker>Κλυταιμήστρα</tei:speaker>
                  <tei:l rend="indent" n="872">ἐκκάλυπτε νῦν ποθʼ ἡμῖν οὕστινας λέγεις λόγους.</tei:l>
               </tei:sp>
               <tei:sp>
                  <tei:speaker>Πρεσβύτης</tei:speaker>
                  <tei:l rend="indent" n="873">παῖδα σὴν πατὴρ ὁ φύσας αὐτόχειρ μέλλει κτενεῖν.</tei:l>
               </tei:sp>
               <tei:sp>
                  <tei:speaker>Κλυταιμήστρα</tei:speaker>
                  <tei:l rend="indent" n="874">πῶς; ἀπέπτυσʼ, ὦ γεραιέ, μῦθον· οὐ γὰρ εὖ φρονεῖς.</tei:l>
               </tei:sp>
               <tei:sp>
                  <tei:speaker>Πρεσβύτης</tei:speaker>
                  <tei:l rend="indent" n="875">φασγάνῳ λευκὴν φονεύων τῆς ταλαιπώρου δέρην.</tei:l>
               </tei:sp>
               <tei:sp>
                  <tei:speaker>Κλυταιμήστρα</tei:speaker>
                  <tei:l rend="indent" n="876">ὦ τάλαινʼ ἐγώ. μεμηνὼς ἆρα τυγχάνει πόσις;</tei:l>
               </tei:sp>
               <tei:sp>
                  <tei:speaker>Πρεσβύτης</tei:speaker>
                  <tei:l rend="indent" n="877">ἀρτίφρων, πλὴν ἐς σὲ καὶ σὴν παῖδα· τοῦτο δʼ οὐ φρονεῖ.</tei:l>
               </tei:sp>
               <tei:sp>
                  <tei:speaker>Κλυταιμήστρα</tei:speaker>
                  <tei:l rend="indent" n="878">ἐκ τίνος λόγου; τίς αὐτὸν οὑπάγων ἀλαστόρων;</tei:l>
               </tei:sp>
               <tei:sp>
                  <tei:speaker>Πρεσβύτης</tei:speaker>
                  <tei:l rend="indent" n="879">θέσφαθʼ, ὥς γέ φησι Κάλχας, ἵνα πορεύηται στρατός.</tei:l>
               </tei:sp>
               <tei:sp>
                  <tei:speaker>Κλυταιμήστρα</tei:speaker>
                  <tei:l rend="indent" n="880">ποῖ; τάλαινʼ ἐγώ, τάλαινα δʼ ἣν πατὴρ μέλλει κτενεῖν.</tei:l>
               </tei:sp>
               <tei:sp>
                  <tei:speaker>Πρεσβύτης</tei:speaker>
                  <tei:l rend="indent" n="881">Δαρδάνου πρὸς δώμαθʼ, Ἑλένην Μενέλεως ὅπως λάβῃ.</tei:l>
               </tei:sp>
               <tei:sp>
                  <tei:speaker>Κλυταιμήστρα</tei:speaker>
                  <tei:l rend="indent" n="882">εἰς ἄρʼ Ἰφιγένειαν Ἑλένης νόστος ἦν πεπρωμένος;</tei:l>
               </tei:sp>
               <tei:sp>
                  <tei:speaker>Πρεσβύτης</tei:speaker>
                  <tei:l rend="indent" n="883">πάντʼ ἔχεις· Ἀρτέμιδι θύσειν παῖδα σὴν μέλλει πατήρ.</tei:l>
               </tei:sp>
               <tei:sp>
                  <tei:speaker>Κλυταιμήστρα</tei:speaker>
                  <tei:l rend="indent" n="884">ὁ δὲ γάμος τίνʼ εἶχε πρόφασιν, ᾧ μʼ ἐκόμισεν ἐκ δόμων;</tei:l>
               </tei:sp>
               <tei:sp>
                  <tei:speaker>Πρεσβύτης</tei:speaker>
                  <tei:l rend="indent" n="885">ἵνʼ ἀγάγοις χαίρουσʼ Ἀχιλλεῖ παῖδα νυμφεύσουσα σήν.</tei:l>
               </tei:sp>
               <tei:sp>
                  <tei:speaker>Κλυταιμήστρα</tei:speaker>
                  <tei:l rend="indent" n="886">ὦ θύγατερ, ἥκεις ἐπʼ ὀλέθρῳ καὶ σὺ καὶ μήτηρ σέθεν.</tei:l>
               </tei:sp>
               <tei:sp>
                  <tei:speaker>Πρεσβύτης</tei:speaker>
                  <tei:l rend="indent" n="887">οἰκτρὰ πάσχετον δύʼ οὖσαι· δεινὰ δʼ Ἀγαμέμνων ἔτλη.</tei:l>
               </tei:sp>
               <tei:sp>
                  <tei:speaker>Κλυταιμήστρα</tei:speaker>
                  <tei:l rend="indent" n="888">οἴχομαι τάλαινα, δακρύων τʼ ὄμματʼ οὐκέτι στέγω.</tei:l>
               </tei:sp>
               <tei:sp>
                  <tei:speaker>Πρεσβύτης</tei:speaker>
                  <tei:l rend="indent" n="889">εἴπερ ἀλγεινὸν τὸ τέκνων στερόμενον, δακρυρρόει.</tei:l>
               </tei:sp>
               <tei:sp>
                  <tei:speaker>Κλυταιμήστρα</tei:speaker>
                  <tei:l rend="indent" n="890">σὺ δὲ τάδʼ, ὦ γέρον, πόθεν φῂς εἰδέναι πεπυσμένος;</tei:l>
               </tei:sp>
               <tei:sp>
                  <tei:speaker>Πρεσβύτης</tei:speaker>
                  <tei:l rend="indent" n="891">δέλτον ᾠχόμην φέρων σοι πρὸς τὰ πρὶν γεγραμμένα.</tei:l>
               </tei:sp>
               <tei:sp>
                  <tei:speaker>Κλυταιμήστρα</tei:speaker>
                  <tei:l rend="indent" n="892">οὐκ ἐῶν ἢ ξυγκελεύων παῖδʼ ἄγειν θανουμένην;</tei:l>
               </tei:sp>
               <tei:sp>
                  <tei:speaker>Πρεσβύτης</tei:speaker>
                  <tei:l rend="indent" n="893">μὴ μὲν οὖν ἄγειν· φρονῶν γὰρ ἔτυχε σὸς πόσις τότʼ εὖ.</tei:l>
               </tei:sp>
               <tei:sp>
                  <tei:speaker>Κλυταιμήστρα</tei:speaker>
                  <tei:l rend="indent" n="894">κᾆτα πῶς φέρων γε δέλτον οὐκ ἐμοὶ δίδως λαβεῖν;</tei:l>
               </tei:sp>
               <tei:sp>
                  <tei:speaker>Πρεσβύτης</tei:speaker>
                  <tei:l rend="indent" n="895">Μενέλεως ἀφείλεθʼ ἡμᾶς, ὃς κακῶν τῶνδʼ αἴτιος.</tei:l>
               </tei:sp>
               <tei:sp>
                  <tei:speaker>Κλυταιμήστρα</tei:speaker>
                  <tei:l rend="indent" n="896">ὦ τέκνον Νηρῇδος, ὦ παῖ Πηλέως, κλύεις τάδε;</tei:l>
               </tei:sp>
               <tei:sp>
                  <tei:speaker>Ἀχιλλεύς</tei:speaker>
                  <tei:l rend="indent" n="897">ἔκλυον οὖσαν ἀθλίαν σε, τὸ δʼ ἐμὸν οὐ φαύλως φέρω.</tei:l>
               </tei:sp>
               <tei:sp>
                  <tei:speaker>Κλυταιμήστρα</tei:speaker>
                  <tei:l rend="indent" n="898">παῖδά μου κατακτενοῦσι σοῖς δολώσαντες γάμοις.</tei:l>
               </tei:sp>
               <tei:sp>
                  <tei:speaker>Ἀχιλλεύς</tei:speaker>
                  <tei:l rend="indent" n="899">μέμφομαι κἀγὼ πόσει σῷ, κοὐχ ἁπλῶς οὕτω φέρω.</tei:l>
               </tei:sp>
               <tei:milestone resp="perseus" unit="card" n="900"/>
               <tei:sp>
                  <tei:speaker>Κλυταιμήστρα</tei:speaker>
                  <tei:l rend="indent" n="900">οὐκ ἐπαιδεσθήσομαί γε προσπεσεῖν τὸ σὸν γόνυ,</tei:l>
                  <tei:l n="901">θνητὸς ἐκ θεᾶς γεγῶτα· τί γὰρ ἐγὼ σεμνύνομαι;</tei:l>
                  <tei:l n="902">ἢ τίνος σπουδαστέον μοι μᾶλλον ἢ τέκνου πέρι;</tei:l>
                  <tei:l n="903">ἀλλʼ ἄμυνον, ὦ θεᾶς παῖ, τῇ τʼ ἐμῇ δυσπραξίᾳ</tei:l>
                  <tei:l n="904">τῇ τε λεχθείσῃ δάμαρτι σῇ — μάτην μέν, ἀλλʼ ὅμως.</tei:l>
                  <tei:l n="905">σοὶ καταστέψασʼ ἐγώ νιν ἦγον ὡς γαμουμένην,</tei:l>
                  <tei:l n="906">νῦν δʼ ἐπὶ σφαγὰς κομίζω· σοὶ δʼ ὄνειδος ἵξεται,</tei:l>
                  <tei:l n="907">ὅστις οὐκ ἤμυνας· εἰ γὰρ μὴ γάμοισιν ἐζύγης,</tei:l>
                  <tei:l n="908">ἀλλʼ ἐκλήθης γοῦν ταλαίνης παρθένου φίλος πόσις.</tei:l>
                  <tei:l n="909">πρὸς γενειάδος <tei:add>σε</tei:add>, πρός σε δεξιᾶς, πρὸς μητέρος — </tei:l>
                  <tei:l n="910">ὄνομα γὰρ τὸ σόν μʼ ἀπώλεσʼ, ᾧ σʼ ἀμυναθεῖν χρεών — </tei:l>
                  <tei:l n="911">οὐκ ἔχω βωμὸν καταφυγεῖν ἄλλον ἢ τὸ σὸν γόνυ·</tei:l>
                  <tei:l n="912">οὐδὲ φίλος οὐδεὶς γελᾷ μοι· τὰ δʼ Ἀγαμέμνονος κλύεις,</tei:l>
                  <tei:l n="913">ὠμὰ καὶ πάντολμʼ· ἀφῖγμαι δʼ, ὥσπερ εἰσορᾷς, γυνὴ</tei:l>
                  <tei:l n="914">ναυτικὸν στράτευμʼ ἄναρχον κἀπὶ τοῖς κακοῖς θρασύ—</tei:l>
                  <tei:l n="915">χρήσιμον δʼ, ὅταν θέλωσιν. ἢν δὲ τολμήσῃς σύ μου</tei:l>
                  <tei:l n="916">χεῖρʼ ὑπερτεῖναι, σεσῴσμεθʼ· εἰ δὲ μή, οὐ σεσῴσμεθα.</tei:l>
               </tei:sp>
            </tei:div>
            <tei:div type="dialogue">
               <tei:milestone resp="perseus" unit="card" n="917"/>
               <tei:sp>
                  <tei:speaker>Χορός</tei:speaker>
                  <tei:l rend="indent" n="917">δεινὸν τὸ τίκτειν καὶ φέρει φίλτρον μέγα</tei:l>
                  <tei:l n="918">πᾶσίν τε κοινὸν ὥσθʼ ὑπερκάμνειν τέκνων.</tei:l>
               </tei:sp>
               <tei:sp>
                  <tei:speaker>Ἀχιλλεύς</tei:speaker>
                  <tei:l rend="indent" n="919">ὑψηλόφρων μοι θυμὸς αἴρεται πρόσω·</tei:l>
                  <tei:l n="920">ἐπίσταμαι δὲ τοῖς κακοῖσί τʼ ἀσχαλᾶν</tei:l>
                  <tei:l n="921">μετρίως τε χαίρειν τοῖσιν ἐξωγκωμένοις.</tei:l>
                  <tei:l n="922">λελογισμένοι γὰρ οἱ τοιοίδʼ εἰσὶν βροτῶν</tei:l>
                  <tei:l n="923">ὀρθῶς διαζῆν τὸν βίον γνώμης μέτα.</tei:l>
                  <tei:l n="924" rend="indent">ἔστιν μὲν οὖν ἵνʼ ἡδὺ μὴ λίαν φρονεῖν,</tei:l>
                  <tei:l n="925">ἔστιν δὲ χὥπου χρήσιμον γνώμην ἔχειν.</tei:l>
                  <tei:l n="926">ἐγὼ δʼ, ἐν ἀνδρὸς εὐσεβεστάτου τραφεὶς</tei:l>
                  <tei:l n="927">Χείρωνος, ἔμαθον τοὺς τρόπους ἁπλοῦς ἔχειν.</tei:l>
                  <tei:l n="928">καὶ τοῖς Ἀτρείδαις, ἢν μὲν ἡγῶνται καλῶς,</tei:l>
                  <tei:l n="929">πεισόμεθʼ, ὅταν δὲ μὴ καλῶς, οὐ πείσομαι.</tei:l>
                  <tei:l n="930">ἀλλʼ ἐνθάδʼ ἐν Τροίᾳ τʼ ἐλευθέραν φύσιν</tei:l>
                  <tei:l n="931">παρέχων, Ἄρη τὸ κατʼ ἐμὲ κοσμήσω δορί.</tei:l>
                  <tei:l n="932" rend="indent">σὲ δʼ, ὦ σχέτλια παθοῦσα πρὸς τῶν φιλτάτων,</tei:l>
                  <tei:l n="933">ἃ δὴ κατʼ ἄνδρα γίγνεται νεανίαν,</tei:l>
                  <tei:l n="934">τοσοῦτον οἶκτον περιβαλὼν καταστελῶ,</tei:l>
                  <tei:l n="935">κοὔποτε κόρη σὴ πρὸς πατρὸς σφαγήσεται,</tei:l>
                  <tei:l n="936">ἐμὴ φατισθεῖσʼ· οὐ γὰρ ἐμπλέκειν πλοκὰς</tei:l>
                  <tei:l n="937">ἐγὼ παρέξω σῷ πόσει τοὐμὸν δέμας.</tei:l>
                  <tei:l n="938">τοὔνομα γάρ, εἰ καὶ μὴ σίδηρον ἤρατο,</tei:l>
                  <tei:l n="939">τοὐμὸν φονεύσει παῖδα σήν. τὸ δʼ αἴτιον</tei:l>
                  <tei:l n="940">πόσις σός. ἁγνὸν δʼ οὐκέτʼ ἐστὶ σῶμʼ ἐμόν,</tei:l>
                  <tei:l n="941">εἰ διʼ ἔμʼ ὀλεῖται διά τε τοὺς ἐμοὺς γάμους</tei:l>
                  <tei:l n="942">ἡ δεινὰ τλᾶσα κοὐκ ἀνεκτὰ παρθένος,</tei:l>
                  <tei:l n="943">θαυμαστὰ δʼ ὡς ἀνάξιʼ ἠτιμασμένη.</tei:l>
                  <tei:milestone resp="perseus" unit="card" n="944"/>
                  <tei:l n="944" rend="indent">ἐγὼ κάκιστος ἦν ἄρʼ Ἀργείων ἀνήρ,</tei:l>
                  <tei:l n="945">ἐγὼ τὸ μηδέν, Μενέλεως δʼ ἐν ἀνδράσιν,</tei:l>
                  <tei:l n="946">ὡς οὐχὶ Πηλέως, ἀλλʼ ἀλάστορος γεγώς,</tei:l>
                  <tei:l n="947">εἴπερ φονεύει τοὐμὸν ὄνομα σῷ πόσει.</tei:l>
                  <tei:l n="948">μὰ τὸν διʼ ὑγρῶν κυμάτων τεθραμμένον</tei:l>
                  <tei:l n="949">Νηρέα, φυτουργὸν Θέτιδος ἥ μʼ ἐγείνατο,</tei:l>
                  <tei:l n="950">οὐχ ἅψεται σῆς θυγατρὸς Ἀγαμέμνων ἄναξ,</tei:l>
                  <tei:l n="951">οὐδʼ εἰς ἄκραν χεῖρʼ, ὥστε προσβαλεῖν πέπλοις·</tei:l>
                  <tei:l n="952">ἢ Σίπυλος ἔσται πόλις, ὅρισμα βαρβάρων,</tei:l>
                  <tei:l n="953">ὅθεν πεφύκασʼ οἱ στρατηλάται γένος,</tei:l>
                  <tei:l n="954">Φθίας δὲ τοὔνομʼ οὐδαμοῦ κεκλήσεται.</tei:l>
                  <tei:l n="955">πικροὺς δὲ προχύτας χέρνιβάς τʼ ἀνάξεται</tei:l>
                  <tei:l n="956">Κάλχας ὁ μάντις. τίς δὲ μάντις ἔστʼ ἀνήρ,</tei:l>
                  <tei:l n="957">ὃς ὀλίγʼ ἀληθῆ, πολλὰ δὲ ψευδῆ λέγει</tei:l>
                  <tei:l n="958">τυχών, ὅταν δὲ μὴ τύχῃ, διοίχεται;</tei:l>
                  <tei:l n="959" rend="indent">οὐ τῶν γάμων ἕκατι — μυρίαι κόραι</tei:l>
                  <tei:l n="960">θηρῶσι λέκτρον τοὐμόν — εἴρηται τόδε·</tei:l>
                  <tei:l n="961">ἀλλʼ ὕβριν ἐς ἡμᾶς ὕβρισʼ Ἀγαμέμνων ἄναξ.</tei:l>
                  <tei:l n="962">χρῆν δʼ αὐτὸν αἰτεῖν τοὐμὸν ὄνομʼ ἐμοῦ πάρα,</tei:l>
                  <tei:l n="963">θήραμα παιδός· ἡ Κλυταιμήστρα δʼ ἐμοὶ</tei:l>
                  <tei:l n="964">μάλιστʼ ἐπείσθη θυγατέρʼ ἐκδοῦναι πόσει.</tei:l>
                  <tei:l n="965">ἔδωκά τἂν Ἕλλησιν, εἰ πρὸς Ἴλιον</tei:l>
                  <tei:l n="966">ἐν τῷδʼ ἔκαμνε νόστος· οὐκ ἠρνούμεθʼ ἂν</tei:l>
                  <tei:l n="967">τὸ κοινὸν αὔξειν ὧν μέτʼ ἐστρατευόμην.</tei:l>
                  <tei:l n="968">νῦν δʼ οὐδέν εἰμι, παρὰ δὲ τοῖς στρατηλάταις</tei:l>
                  <tei:l n="969">ἐν εὐμαρεῖ με δρᾶν τε καὶ μὴ δρᾶν κακῶς.</tei:l>
                  <tei:l n="970">τάχʼ εἴσεται σίδηρος, ὃν πρὶν ἐς Φρύγας</tei:l>
                  <tei:l n="971">ἐλθεῖν, <tei:sic>φόνου κηλῖσιν αἵματι</tei:sic> χρανῶ,</tei:l>
                  <tei:l n="972">εἴ τίς με τὴν σὴν θυγατέρʼ ἐξαιρήσεται.</tei:l>
                  <tei:l n="973" rend="indent">ἀλλʼ ἡσύχαζε· θεὸς ἐγὼ πέφηνά σοι</tei:l>
                  <tei:l n="974">μέγιστος, οὐκ ὤν· ἀλλʼ ὅμως γενήσομαι.</tei:l>
               </tei:sp>
               <tei:sp>
                  <tei:speaker>Χορός</tei:speaker>
                  <tei:l rend="indent" n="975">ἔλεξας, ὦ παῖ Πηλέως, σοῦ τʼ ἄξια</tei:l>
                  <tei:l n="976">καὶ τῆς ἐναλίας δαίμονος, σεμνῆς θεοῦ.</tei:l>
               </tei:sp>
               <tei:sp>
                  <tei:speaker>Κλυταιμήστρα</tei:speaker>
                  <tei:l rend="indent" n="977">φεῦ·</tei:l>
                  <tei:l n="977a">πῶς ἄν σʼ ἐπαινέσαιμι μὴ λίαν λόγοις,</tei:l>
                  <tei:l n="978">μηδʼ ἐνδεὴς τοῦδʼ ἀπολέσαιμι τὴν χάριν;</tei:l>
                  <tei:l n="979">αἰνούμενοι γὰρ οἱ ἀγαθοὶ τρόπον τινὰ</tei:l>
                  <tei:l n="980">μισοῦσι τοὺς αἰνοῦντας, ἢν αἰνῶσʼ ἄγαν.</tei:l>
                  <tei:l n="981">αἰσχύνομαι δὲ παραφέρουσʼ οἰκτροὺς λόγους,</tei:l>
                  <tei:l n="982">ἰδίᾳ νοσοῦσα· σὺ δʼ ἄνοσος κακῶν ἐμῶν.</tei:l>
                  <tei:l n="983">ἀλλʼ οὖν ἔχει τοι σχῆμα, κἂν ἄπωθεν ᾖ</tei:l>
                  <tei:l n="984">ἀνὴρ ὁ χρηστός, δυστυχοῦντας ὠφελεῖν.</tei:l>
                  <tei:l n="985">οἴκτιρε δʼ ἡμᾶς· οἰκτρὰ γὰρ πεπόνθαμεν·</tei:l>
                  <tei:l n="986">ἣ πρῶτα μέν σε γαμβρὸν οἰηθεῖσʼ ἔχειν,</tei:l>
                  <tei:l n="987">κενὴν κατέσχον ἐλπίδʼ· εἶτά σοι τάχα</tei:l>
                  <tei:l n="988">ὄρνις γένοιτʼ ἂν τοῖσι μέλλουσιν γάμοις</tei:l>
                  <tei:l n="989">θανοῦσʼ ἐμὴ παῖς, ὅ σε φυλάξασθαι χρεών.</tei:l>
                  <tei:l n="990" rend="indent">ἀλλʼ εὖ μὲν ἀρχὰς εἶπας, εὖ δὲ καὶ τέλη·</tei:l>
                  <tei:l n="991">σοῦ γὰρ θέλοντος παῖς ἐμὴ σωθήσεται.</tei:l>
                  <tei:milestone resp="perseus" unit="card" n="992"/>
                  <tei:l n="992" rend="indent">βούλῃ νιν ἱκέτιν σὸν περιπτύξαι γόνυ;</tei:l>
                  <tei:l n="993">ἀπαρθένευτα μὲν τάδʼ· εἰ δέ σοι δοκεῖ,</tei:l>
                  <tei:l n="994">ἥξει, διʼ αἰδοῦς ὄμμʼ ἔχουσʼ ἐλεύθερον.</tei:l>
                  <tei:l n="995">εἰ δʼ οὐ παρούσης ταὐτὰ τεύξομαι σέθεν,</tei:l>
                  <tei:l n="996">μενέτω κατʼ οἴκους· σεμνὰ γὰρ σεμνύνεται.</tei:l>
                  <tei:l n="997">ὅμως δʼ ὅσον γε δυνατὸν αἰδεῖσθαι χρεών.</tei:l>
               </tei:sp>
               <tei:sp>
                  <tei:speaker>Ἀχιλλεύς</tei:speaker>
                  <tei:l rend="indent" n="998">σὺ μήτε σὴν παῖδʼ ἔξαγʼ ὄψιν εἰς ἐμήν,</tei:l>
                  <tei:l n="999">μήτʼ εἰς ὄνειδος ἀμαθὲς ἔλθωμεν, γύναι·</tei:l>
                  <tei:l n="1000">στρατὸς γὰρ ἀθρόος, ἀργὸς ὢν τῶν οἴκοθεν,</tei:l>
                  <tei:l n="1001">λέσχας πονηρὰς καὶ κακοστόμους φιλεῖ.</tei:l>
                  <tei:l n="1002">πάντως δέ μʼ ἱκετεύοντέ θʼ ἥξετʼ εἰς ἴσον,</tei:l>
                  <tei:l n="1003">εἴ τʼ ἀνικέτευτος· εἷς ἐμοὶ γάρ ἐστʼ ἀγὼν</tei:l>
                  <tei:l n="1004">μέγιστος ὑμᾶς ἐξαπαλλάξαι κακῶν.</tei:l>
                  <tei:l n="1005">ὡς ἕν γʼ ἀκούσασʼ ἴσθι, μὴ ψευδῶς μʼ ἐρεῖν·</tei:l>
                  <tei:l n="1006">ψευδῆ λέγων δὲ καὶ μάτην ἐγκερτομῶν,</tei:l>
                  <tei:l n="1007">θάνοιμι· μὴ θάνοιμι δʼ, ἢν σῴσω κόρην.</tei:l>
               </tei:sp>
               <tei:sp>
                  <tei:speaker>Κλυταιμήστρα</tei:speaker>
                  <tei:l rend="indent" n="1008">ὄναιο συνεχῶς δυστυχοῦντας ὠφελῶν.</tei:l>
               </tei:sp>
               <tei:sp>
                  <tei:speaker>Ἀχιλλεύς</tei:speaker>
                  <tei:l rend="indent" n="1009">ἄκουε δή νυν, ἵνα τὸ πρᾶγμʼ ἔχῃ καλῶς.</tei:l>
               </tei:sp>
               <tei:sp>
                  <tei:speaker>Κλυταιμήστρα</tei:speaker>
                  <tei:l rend="indent" n="1010">τί τοῦτʼ ἔλεξας; ὡς ἀκουστέον γέ σου.</tei:l>
               </tei:sp>
               <tei:sp>
                  <tei:speaker>Ἀχιλλεύς</tei:speaker>
                  <tei:l rend="indent" n="1011">
                     <tei:sic>πειθώμεθʼ αὖτις</tei:sic> πατέρα βέλτιον φρονεῖν.</tei:l>
               </tei:sp>
               <tei:sp>
                  <tei:speaker>Κλυταιμήστρα</tei:speaker>
                  <tei:l rend="indent" n="1012">κακός τίς ἐστι καὶ λίαν ταρβεῖ στρατόν.</tei:l>
               </tei:sp>
               <tei:sp>
                  <tei:speaker>Ἀχιλλεύς</tei:speaker>
                  <tei:l rend="indent" n="1013">ἀλλʼ οἱ λόγοι γε καταπαλαίουσιν λόγους.</tei:l>
               </tei:sp>
               <tei:sp>
                  <tei:speaker>Κλυταιμήστρα</tei:speaker>
                  <tei:l rend="indent" n="1014">ψυχρὰ μὲν ἐλπίς· ὅ τι δὲ χρή με δρᾶν φράσον.</tei:l>
               </tei:sp>
               <tei:sp>
                  <tei:speaker>Ἀχιλλεύς</tei:speaker>
                  <tei:l rend="indent" n="1015">ἱκέτευʼ ἐκεῖνον πρῶτα μὴ κτείνειν τέκνα·</tei:l>
                  <tei:l n="1016">ἢν δʼ ἀντιβαίνῃ, πρὸς ἐμέ σοι πορευτέον.</tei:l>
                  <tei:l n="1017">ᾗ γὰρ τὸ χρῇζον ἐπίθετʼ, οὐ τοὐμὸν χρεὼν</tei:l>
                  <tei:l n="1018">χωρεῖν· ἔχει γὰρ αὐτὸ τὴν σωτηρίαν.</tei:l>
                  <tei:l n="1019">κἀγώ τʼ ἀμείνων πρὸς φίλον γενήσομαι,</tei:l>
                  <tei:l n="1020">στρατός τʼ ἂν οὐ μέμψαιτό μʼ, εἰ τὰ πράγματα</tei:l>
                  <tei:l n="1021">λελογισμένως πράσσοιμι μᾶλλον ἢ σθένει.</tei:l>
                  <tei:l n="1022">
                     <tei:sic>καλῶς δὲ κρανθέντων <tei:del>καὶ</tei:del> πρὸς ἡδονὴν φίλοις</tei:sic>
                  </tei:l>
                  <tei:l n="1023">
                     <tei:sic>σοί τʼ ἂν γένοιτο κἂν ἐμοῦ χωρὶς τάδε.</tei:sic>
                  </tei:l>
               </tei:sp>
               <tei:sp>
                  <tei:speaker>Κλυταιμήστρα</tei:speaker>
                  <tei:l rend="indent" n="1024">ὡς σώφρονʼ εἶπας. δραστέον δʼ ἅ σοι δοκεῖ.</tei:l>
                  <tei:l n="1025">ἢν δʼ αὖ τι μὴ πράσσωμεν ὧν ἐγὼ θέλω,</tei:l>
                  <tei:l n="1026">ποῦ σʼ αὖθις ὀψόμεσθα, ποῦ; χρή μʼ ἀθλίαν</tei:l>
                  <tei:l n="1027">ἐλθοῦσαν εὑρεῖν σὴν χέρʼ ἐπίκουρον κακῶν;</tei:l>
               </tei:sp>
               <tei:sp>
                  <tei:speaker>Ἀχιλλεύς</tei:speaker>
                  <tei:l rend="indent" n="1028">ἡμεῖς σε φύλακες οὗ χρεὼν φυλάξομεν,</tei:l>
                  <tei:l n="1029">μή τίς σʼ ἴδῃ στείχουσαν ἐπτοημένην</tei:l>
                  <tei:l n="1030">Δαναῶν διʼ ὄχλου· μηδὲ πατρῷον δόμον</tei:l>
                  <tei:l n="1031">αἴσχυνʼ· ὁ γάρ τοι Τυνδάρεως οὐκ ἄξιος</tei:l>
                  <tei:l n="1032">κακῶς ἀκούειν· ἐν γὰρ Ἕλλησιν μέγας.</tei:l>
               </tei:sp>
               <tei:sp>
                  <tei:speaker>Κλυταιμήστρα</tei:speaker>
                  <tei:l rend="indent" n="1033">ἔστιν τάδʼ· ἄρχε· σοί με δουλεύειν χρεών.</tei:l>
                  <tei:l n="1034">εἰ δʼ εἰσὶ θεοί, δίκαιος ὢν ἀνὴρ <tei:add>θεῶν</tei:add>
                  </tei:l>
                  <tei:l n="1035">ἐσθλῶν κυρήσεις· εἰ δὲ μή, τί δεῖ πονεῖν;</tei:l>
               </tei:sp>
            </tei:div>
         </tei:div>
         </elements>
</citationChunk>
