<?xml version='1.0' encoding='utf-8'?>
<citationChunk xmlns:tei="http://www.tei-c.org/ns/1.0" unit="line" base_urn="urn:cts:greekLit:tlg0012.tlg001.perseus-grc2" cts_urn="urn:cts:greekLit:tlg0012.tlg001.perseus-grc2:15.379" prev_urn="urn:cts:greekLit:tlg0012.tlg001.perseus-grc2:15.343" next_urn="urn:cts:greekLit:tlg0012.tlg001.perseus-grc2:15.592">
  <elements><tei:div type="card" n="379">
					<tei:l n="379">
						<tei:milestone ed="P" unit="para"/>Τρῶες δʼ ὡς ἐπύθοντο Διὸς κτύπον αἰγιόχοιο,</tei:l>
					<tei:l n="380">μᾶλλον ἐπʼ Ἀργείοισι θόρον, μνήσαντο δὲ χάρμης.</tei:l>
					<tei:l n="381">οἳ δʼ ὥς τε μέγα κῦμα θαλάσσης εὐρυπόροιο</tei:l>
					<tei:l n="382">νηὸς ὑπὲρ τοίχων καταβήσεται, ὁππότʼ ἐπείγῃ</tei:l>
					<tei:l n="383">ἲς ἀνέμου· ἣ γάρ τε μάλιστά γε κύματʼ ὀφέλλει·</tei:l>
					<tei:l n="384">ὣς Τρῶες μεγάλῃ ἰαχῇ κατὰ τεῖχος ἔβαινον,</tei:l>
					<tei:l n="385">ἵππους δʼ εἰσελάσαντες ἐπὶ πρύμνῃσι μάχοντο</tei:l>
					<tei:l n="386">ἔγχεσιν ἀμφιγύοις αὐτοσχεδόν, οἳ μὲν ἀφʼ ἵππων,</tei:l>
					<tei:l n="387">οἳ δʼ ἀπὸ νηῶν ὕψι μελαινάων ἐπιβάντες</tei:l>
					<tei:l n="388">μακροῖσι ξυστοῖσι, τά ῥά σφʼ ἐπὶ νηυσὶν ἔκειτο</tei:l>
					<tei:l n="389">ναύμαχα κολλήεντα, κατὰ στόμα εἱμένα χαλκῷ.</tei:l>
					<tei:l n="390">
						<tei:milestone ed="P" unit="para"/>Πάτροκλος δʼ εἷος μὲν Ἀχαιοί τε Τρῶές τε</tei:l>
					<tei:l n="391">τείχεος ἀμφεμάχοντο θοάων ἔκτοθι νηῶν,</tei:l>
					<tei:l n="392">τόφρʼ ὅ γʼ ἐνὶ κλισίῃ ἀγαπήνορος Εὐρυπύλοιο</tei:l>
					<tei:l n="393">ἧστό τε καὶ τὸν ἔτερπε λόγοις, ἐπὶ δʼ ἕλκεϊ λυγρῷ</tei:l>
					<tei:l n="394">φάρμακʼ ἀκέσματʼ ἔπασσε μελαινάων ὀδυνάων.</tei:l>
					<tei:l n="395">αὐτὰρ ἐπεὶ δὴ τεῖχος ἐπεσσυμένους ἐνόησε</tei:l>
					<tei:l n="396">Τρῶας, ἀτὰρ Δαναῶν γένετο ἰαχή τε φόβος τε,</tei:l>
					<tei:l n="397">ᾤμωξέν τʼ ἄρʼ ἔπειτα καὶ ὣ πεπλήγετο μηρὼ</tei:l>
					<tei:l n="398">χερσὶ καταπρηνέσσʼ, ὀλοφυρόμενος δʼ ἔπος ηὔδα·</tei:l>
					<tei:q>
						<tei:l n="399">Εὐρύπυλʼ οὐκ ἔτι τοι δύναμαι χατέοντί περʼ ἔμπης</tei:l>
						<tei:l n="400">ἐνθάδε παρμενέμεν· δὴ γὰρ μέγα νεῖκος ὄρωρεν·</tei:l>
						<tei:l n="401">ἀλλὰ σὲ μὲν θεράπων ποτιτερπέτω, αὐτὰρ ἔγωγε</tei:l>
						<tei:l n="402">σπεύσομαι εἰς Ἀχιλῆα, ἵνʼ ὀτρύνω πολεμίζειν.</tei:l>
						<tei:l n="403">τίς δʼ οἶδʼ εἴ κέν οἱ σὺν δαίμονι θυμὸν ὀρίνω</tei:l>
						<tei:l n="404">παρειπών; ἀγαθὴ δὲ παραίφασίς ἐστιν ἑταίρου.</tei:l>
						<tei:milestone ed="p" n="405" unit="card"/>
					</tei:q>
					<tei:l n="405">
						<tei:milestone ed="P" unit="para"/>τὸν μὲν ἄρʼ ὣς εἰπόντα πόδες φέρον· αὐτὰρ
						Ἀχαιοὶ</tei:l>
					<tei:l n="406">Τρῶας ἐπερχομένους μένον ἔμπεδον, οὐδʼ ἐδύναντο</tei:l>
					<tei:l n="407">παυροτέρους περ ἐόντας ἀπώσασθαι παρὰ νηῶν·</tei:l>
					<tei:l n="408">οὐδέ ποτε Τρῶες Δαναῶν ἐδύναντο φάλαγγας</tei:l>
					<tei:l n="409">ῥηξάμενοι κλισίῃσι μιγήμεναι ἠδὲ νέεσσιν.</tei:l>
					<tei:l n="410">ἀλλʼ ὥς τε στάθμη δόρυ νήϊον ἐξιθύνει</tei:l>
					<tei:l n="411">τέκτονος ἐν παλάμῃσι δαήμονος, ὅς ῥά τε πάσης</tei:l>
					<tei:l n="412">εὖ εἰδῇ σοφίης ὑποθημοσύνῃσιν Ἀθήνης,</tei:l>
					<tei:l n="413">ὣς μὲν τῶν ἐπὶ ἶσα μάχη τέτατο πτόλεμός τε·</tei:l>
					<tei:l n="414">ἄλλοι δʼ ἀμφʼ ἄλλῃσι μάχην ἐμάχοντο νέεσσιν,</tei:l>
					<tei:l n="415">Ἕκτωρ δʼ ἄντʼ Αἴαντος ἐείσατο κυδαλίμοιο.</tei:l>
					<tei:l n="416">τὼ δὲ μιῆς περὶ νηὸς ἔχον πόνον, οὐδὲ δύναντο</tei:l>
					<tei:l n="417">οὔθʼ ὃ τὸν ἐξελάσαι καὶ ἐνιπρῆσαι πυρὶ νῆα</tei:l>
					<tei:l n="418">οὔθʼ ὃ τὸν ἂψ ὤσασθαι, ἐπεί ῥʼ ἐπέλασσέ γε δαίμων.</tei:l>
					<tei:l n="419">ἔνθʼ υἷα Κλυτίοιο Καλήτορα φαίδιμος Αἴας</tei:l>
					<tei:l n="420">πῦρ ἐς νῆα φέροντα κατὰ στῆθος βάλε δουρί.</tei:l>
					<tei:l n="421">δούπησεν δὲ πεσών, δαλὸς δέ οἱ ἔκπεσε χειρός.</tei:l>
					<tei:l n="422">Ἕκτωρ δʼ ὡς ἐνόησεν ἀνεψιὸν ὀφθαλμοῖσιν</tei:l>
					<tei:l n="423">ἐν κονίῃσι πεσόντα νεὸς προπάροιθε μελαίνης,</tei:l>
					<tei:l n="424">Τρωσί τε καὶ Λυκίοισιν ἐκέκλετο μακρὸν ἀΰσας·</tei:l>
					<tei:q>
						<tei:l n="425">Τρῶες καὶ Λύκιοι καὶ Δάρδανοι ἀγχιμαχηταὶ</tei:l>
						<tei:l n="426">μὴ δή πω χάζεσθε μάχης ἐν στείνεϊ τῷδε,</tei:l>
						<tei:l n="427">ἀλλʼ υἷα Κλυτίοιο σαώσατε, μή μιν Ἀχαιοὶ</tei:l>
						<tei:l n="428">τεύχεα συλήσωσι νεῶν ἐν ἀγῶνι πεσόντα.</tei:l>
					</tei:q>
					<tei:l n="429">
						<tei:milestone ed="P" unit="para"/>ὣς εἰπὼν Αἴαντος ἀκόντισε δουρὶ φαεινῷ.</tei:l>
					<tei:l n="430">τοῦ μὲν ἅμαρθʼ, ὃ δʼ ἔπειτα Λυκόφρονα Μάστορος υἱὸν</tei:l>
					<tei:l n="431">Αἴαντος θεράποντα Κυθήριον, ὅς ῥα παρʼ αὐτῷ</tei:l>
					<tei:l n="432">ναῖʼ, ἐπεὶ ἄνδρα κατέκτα Κυθήροισι ζαθέοισι,</tei:l>
					<tei:l n="433">τόν ῥʼ ἔβαλεν κεφαλὴν ὑπὲρ οὔατος ὀξέϊ χαλκῷ</tei:l>
					<tei:l n="434">ἑσταότʼ ἄγχʼ Αἴαντος· ὃ δʼ ὕπτιος ἐν κονίῃσι</tei:l>
					<tei:l n="435">νηὸς ἄπο πρυμνῆς χαμάδις πέσε, λύντο δὲ γυῖα.</tei:l>
					<tei:l n="436">Αἴας δʼ ἐρρίγησε, κασίγνητον δὲ προσηύδα·</tei:l>
					<tei:q>
						<tei:l n="437">Τεῦκρε πέπον δὴ νῶϊν ἀπέκτατο πιστὸς ἑταῖρος</tei:l>
						<tei:l n="438">Μαστορίδης, ὃν νῶϊ Κυθηρόθεν ἔνδον ἐόντα</tei:l>
						<tei:l n="439">ἶσα φίλοισι τοκεῦσιν ἐτίομεν ἐν μεγάροισι·</tei:l>
						<tei:l n="440">τὸν δʼ Ἕκτωρ μεγάθυμος ἀπέκτανε. ποῦ νύ τοι ἰοὶ</tei:l>
						<tei:l n="441">ὠκύμοροι καὶ τόξον ὅ τοι πόρε Φοῖβος Ἀπόλλων;</tei:l>
						<tei:milestone ed="p" n="442" unit="card"/>
					</tei:q>
					<tei:l n="442">
						<tei:milestone ed="P" unit="para"/>ὣς φάθʼ, ὃ δὲ ξυνέηκε, θέων δέ οἱ ἄγχι
						παρέστη,</tei:l>
					<tei:l n="443">τόξον ἔχων ἐν χειρὶ παλίντονον ἠδὲ φαρέτρην</tei:l>
					<tei:l n="444">ἰοδόκον· μάλα δʼ ὦκα βέλεα Τρώεσσιν ἐφίει.</tei:l>
					<tei:l n="445">καί ῥʼ ἔβαλε Κλεῖτον Πεισήνορος ἀγλαὸν υἱὸν</tei:l>
					<tei:l n="446">Πουλυδάμαντος ἑταῖρον ἀγαυοῦ Πανθοΐδαο</tei:l>
					<tei:l n="447">ἡνία χερσὶν ἔχοντα· ὃ μὲν πεπόνητο καθʼ ἵππους·</tei:l>
					<tei:l n="448">τῇ γὰρ ἔχʼ ᾗ ῥα πολὺ πλεῖσται κλονέοντο φάλαγγες</tei:l>
					<tei:l n="449">Ἕκτορι καὶ Τρώεσσι χαριζόμενος· τάχα δʼ αὐτῷ</tei:l>
					<tei:l n="450">ἦλθε κακόν, τό οἱ οὔ τις ἐρύκακεν ἱεμένων περ.</tei:l>
					<tei:l n="451">αὐχένι γάρ οἱ ὄπισθε πολύστονος ἔμπεσεν ἰός·</tei:l>
					<tei:l n="452">ἤριπε δʼ ἐξ ὀχέων, ὑπερώησαν δέ οἱ ἵπποι</tei:l>
					<tei:l n="453">κείνʼ ὄχεα κροτέοντες. ἄναξ δʼ ἐνόησε τάχιστα</tei:l>
					<tei:l n="454">Πουλυδάμας, καὶ πρῶτος ἐναντίος ἤλυθεν ἵππων.</tei:l>
					<tei:l n="455">τοὺς μὲν ὅ γʼ Ἀστυνόῳ Προτιάονος υἱέϊ δῶκε,</tei:l>
					<tei:l n="456">πολλὰ δʼ ἐπότρυνε σχεδὸν ἴσχειν εἰσορόωντα</tei:l>
					<tei:l n="457">ἵππους· αὐτὸς δʼ αὖτις ἰὼν προμάχοισιν ἐμίχθη.</tei:l>
					<tei:l n="458">
						<tei:milestone ed="P" unit="para"/>Τεῦκρος δʼ ἄλλον ὀϊστὸν ἐφʼ Ἕκτορι
						χαλκοκορυστῇ</tei:l>
					<tei:l n="459">αἴνυτο, καί κεν ἔπαυσε μάχης ἐπὶ νηυσὶν Ἀχαιῶν,</tei:l>
					<tei:l n="460">εἴ μιν ἀριστεύοντα βαλὼν ἐξείλετο θυμόν.</tei:l>
					<tei:l n="461">ἀλλʼ οὐ λῆθε Διὸς πυκινὸν νόον, ὅς ῥʼ ἐφύλασσεν</tei:l>
					<tei:l n="462">Ἕκτορʼ, ἀτὰρ Τεῦκρον Τελαμώνιον εὖχος ἀπηύρα,</tei:l>
					<tei:l n="463">ὅς οἱ ἐϋστρεφέα νευρὴν ἐν ἀμύμονι τόξῳ</tei:l>
					<tei:l n="464">ῥῆξʼ ἐπὶ τῷ ἐρύοντι· παρεπλάγχθη δέ οἱ ἄλλῃ</tei:l>
					<tei:l n="465">ἰὸς χαλκοβαρής, τόξον δέ οἱ ἔκπεσε χειρός.</tei:l>
					<tei:l n="466">Τεῦκρος δʼ ἐρρίγησε, κασίγνητον δὲ προσηύδα·</tei:l>
					<tei:q>
						<tei:l n="467">ὢ πόποι ἦ δὴ πάγχυ μάχης ἐπὶ μήδεα κείρει</tei:l>
						<tei:l n="468">δαίμων ἡμετέρης, ὅ τέ μοι βιὸν ἔκβαλε χειρός,</tei:l>
						<tei:l n="469">νευρὴν δʼ ἐξέρρηξε νεόστροφον, ἣν ἐνέδησα</tei:l>
						<tei:l n="470">πρώϊον, ὄφρʼ ἀνέχοιτο θαμὰ θρῴσκοντας ὀϊστούς.</tei:l>
					</tei:q>
					<tei:l n="471">
						<tei:milestone ed="P" unit="para"/>τὸν δʼ ἠμείβετʼ ἔπειτα μέγας Τελαμώνιος
						Αἴας·</tei:l>
					<tei:q>
						<tei:l n="472">ὦ πέπον ἀλλὰ βιὸν μὲν ἔα καὶ ταρφέας ἰοὺς</tei:l>
						<tei:l n="473">κεῖσθαι, ἐπεὶ συνέχευε θεὸς Δαναοῖσι μεγήρας·</tei:l>
						<tei:l n="474">αὐτὰρ χερσὶν ἑλὼν δολιχὸν δόρυ καὶ σάκος ὤμῳ</tei:l>
						<tei:l n="475">μάρναό τε Τρώεσσι καὶ ἄλλους ὄρνυθι λαούς.</tei:l>
						<tei:l n="476">μὴ μὰν ἀσπουδί γε δαμασσάμενοί περ ἕλοιεν</tei:l>
						<tei:l n="477">νῆας ἐϋσσέλμους, ἀλλὰ μνησώμεθα χάρμης.</tei:l>
						<tei:milestone ed="p" n="478" unit="card"/>
					</tei:q>
					<tei:l n="478">
						<tei:milestone ed="P" unit="para"/>ὣς φάθʼ, ὃ δὲ τόξον μὲν ἐνὶ κλισίῃσιν
						ἔθηκεν,</tei:l>
					<tei:l n="479">αὐτὰρ ὅ γʼ ἀμφʼ ὤμοισι σάκος θέτο τετραθέλυμνον,</tei:l>
					<tei:l n="480">κρατὶ δʼ ἐπʼ ἰφθίμῳ κυνέην εὔτυκτον ἔθηκεν</tei:l>
					<tei:l n="481">ἵππουριν, δεινὸν δὲ λόφος καθύπερθεν ἔνευεν·</tei:l>
					<tei:l n="482">εἵλετο δʼ ἄλκιμον ἔγχος ἀκαχμένον ὀξέϊ χαλκῷ,</tei:l>
					<tei:l n="483">βῆ δʼ ἰέναι, μάλα δʼ ὦκα θέων Αἴαντι παρέστη.</tei:l>
					<tei:l n="484">
						<tei:milestone ed="P" unit="para"/>Ἕκτωρ δʼ ὡς εἶδεν Τεύκρου βλαφθέντα βέλεμνα,</tei:l>
					<tei:l n="485">Τρωσί τε καὶ Λυκίοισιν ἐκέκλετο μακρὸν ἀΰσας·</tei:l>
					<tei:q>
						<tei:l n="486">Τρῶες καὶ Λύκιοι καὶ Δάρδανοι ἀγχιμαχηταὶ</tei:l>
						<tei:l n="487">ἀνέρες ἔστε φίλοι, μνήσασθε δὲ θούριδος ἀλκῆς</tei:l>
						<tei:l n="488">νῆας ἀνὰ γλαφυράς· δὴ γὰρ ἴδον ὀφθαλμοῖσιν</tei:l>
						<tei:l n="489">ἀνδρὸς ἀριστῆος Διόθεν βλαφθέντα βέλεμνα.</tei:l>
						<tei:l n="490">ῥεῖα δʼ ἀρίγνωτος Διὸς ἀνδράσι γίγνεται ἀλκή,</tei:l>
						<tei:l n="491">ἠμὲν ὁτέοισιν κῦδος ὑπέρτερον ἐγγυαλίξῃ,</tei:l>
						<tei:l n="492">ἠδʼ ὅτινας μινύθῃ τε καὶ οὐκ ἐθέλῃσιν ἀμύνειν,</tei:l>
						<tei:l n="493">ὡς νῦν Ἀργείων μινύθει μένος, ἄμμι δʼ ἀρήγει.</tei:l>
						<tei:l n="494">ἀλλὰ μάχεσθʼ ἐπὶ νηυσὶν ἀολλέες· ὃς δέ κεν ὑμέων</tei:l>
						<tei:l n="495">βλήμενος ἠὲ τυπεὶς θάνατον καὶ πότμον ἐπίσπῃ</tei:l>
						<tei:l n="496">τεθνάτω· οὔ οἱ ἀεικὲς ἀμυνομένῳ περὶ πάτρης</tei:l>
						<tei:l n="497">τεθνάμεν· ἀλλʼ ἄλοχός τε σόη καὶ παῖδες ὀπίσσω,</tei:l>
						<tei:l n="498">καὶ οἶκος καὶ κλῆρος ἀκήρατος, εἴ κεν Ἀχαιοὶ</tei:l>
						<tei:l n="499">οἴχωνται σὺν νηυσὶ φίλην ἐς πατρίδα γαῖαν.</tei:l>
					</tei:q>
					<tei:l n="500">
						<tei:milestone ed="P" unit="para"/>ὣς εἰπὼν ὄτρυνε μένος καὶ θυμὸν ἑκάστου.</tei:l>
					<tei:l n="501">Αἴας δʼ αὖθʼ ἑτέρωθεν ἐκέκλετο οἷς ἑτάροισιν·</tei:l>
					<tei:q>
						<tei:l n="502">αἰδὼς Ἀργεῖοι· νῦν ἄρκιον ἢ ἀπολέσθαι</tei:l>
						<tei:l n="503">ἠὲ σαωθῆναι καὶ ἀπώσασθαι κακὰ νηῶν.</tei:l>
						<tei:l n="504">ἦ ἔλπεσθʼ ἢν νῆας ἕλῃ κορυθαίολος Ἕκτωρ</tei:l>
						<tei:l n="505">ἐμβαδὸν ἵξεσθαι ἣν πατρίδα γαῖαν ἕκαστος;</tei:l>
						<tei:l n="506">ἦ οὐκ ὀτρύνοντος ἀκούετε λαὸν ἅπαντα</tei:l>
						<tei:l n="507">Ἕκτορος, ὃς δὴ νῆας ἐνιπρῆσαι μενεαίνει;</tei:l>
						<tei:l n="508">οὐ μὰν ἔς γε χορὸν κέλετʼ ἐλθέμεν, ἀλλὰ μάχεσθαι.</tei:l>
						<tei:l n="509">ἡμῖν δʼ οὔ τις τοῦδε νόος καὶ μῆτις ἀμείνων</tei:l>
						<tei:l n="510">ἢ αὐτοσχεδίῃ μῖξαι χεῖράς τε μένος τε.</tei:l>
						<tei:l n="511">βέλτερον ἢ ἀπολέσθαι ἕνα χρόνον ἠὲ βιῶναι</tei:l>
						<tei:l n="512">ἢ δηθὰ στρεύγεσθαι ἐν αἰνῇ δηϊοτῆτι</tei:l>
						<tei:l n="513">ὧδʼ αὔτως παρὰ νηυσὶν ὑπʼ ἀνδράσι χειροτέροισιν.</tei:l>
						<tei:milestone ed="p" n="514" unit="card"/>
					</tei:q>
					<tei:l n="514">
						<tei:milestone ed="P" unit="para"/>ὣς εἰπὼν ὄτρυνε μένος καὶ θυμὸν ἑκάστου.</tei:l>
					<tei:l n="515">ἔνθʼ Ἕκτωρ μὲν ἕλε Σχεδίον Περιμήδεος υἱὸν</tei:l>
					<tei:l n="516">ἀρχὸν Φωκήων, Αἴας δʼ ἕλε Λαοδάμαντα</tei:l>
					<tei:l n="517">ἡγεμόνα πρυλέων Ἀντήνορος ἀγλαὸν υἱόν·</tei:l>
					<tei:l n="518">Πουλυδάμας δʼ Ὦτον Κυλλήνιον ἐξενάριξε</tei:l>
					<tei:l n="519">Φυλεΐδεω ἕταρον, μεγαθύμων ἀρχὸν Ἐπειῶν.</tei:l>
					<tei:l n="520">τῷ δὲ Μέγης ἐπόρουσεν ἰδών· ὃ δʼ ὕπαιθα λιάσθη</tei:l>
					<tei:l n="521">Πουλυδάμας· καὶ τοῦ μὲν ἀπήμβροτεν· οὐ γὰρ Ἀπόλλων</tei:l>
					<tei:l n="522">εἴα Πάνθου υἱὸν ἐνὶ προμάχοισι δαμῆναι·</tei:l>
					<tei:l n="523">αὐτὰρ ὅ γε Κροίσμου στῆθος μέσον οὔτασε δουρί.</tei:l>
					<tei:l n="524">δούπησεν δὲ πεσών· ὃ δʼ ἀπʼ ὤμων τεύχεʼ ἐσύλα.</tei:l>
					<tei:l n="525">τόφρα δὲ τῷ ἐπόρουσε Δόλοψ αἰχμῆς ἐῢ εἰδὼς</tei:l>
					<tei:l n="526">Λαμπετίδης, ὃν Λάμπος ἐγείνατο φέρτατον υἱὸν</tei:l>
					<tei:l n="527">Λαομεδοντιάδης εὖ εἰδότα θούριδος ἀλκῆς,</tei:l>
					<tei:l n="528">ὃς τότε Φυλεΐδαο μέσον σάκος οὔτασε δουρὶ</tei:l>
					<tei:l n="529">ἐγγύθεν ὁρμηθείς· πυκινὸς δέ οἱ ἤρκεσε θώρηξ,</tei:l>
					<tei:l n="530">τόν ῥʼ ἐφόρει γυάλοισιν ἀρηρότα· τόν ποτε Φυλεὺς</tei:l>
					<tei:l n="531">ἤγαγεν ἐξ Ἐφύρης, ποταμοῦ ἄπο Σελλήεντος.</tei:l>
					<tei:l n="532">ξεῖνος γάρ οἱ ἔδωκεν ἄναξ ἀνδρῶν Εὐφήτης</tei:l>
					<tei:l n="533">ἐς πόλεμον φορέειν δηΐων ἀνδρῶν ἀλεωρήν·</tei:l>
					<tei:l n="534">ὅς οἱ καὶ τότε παιδὸς ἀπὸ χροὸς ἤρκεσʼ ὄλεθρον.</tei:l>
					<tei:l n="535">τοῦ δὲ Μέγης κόρυθος χαλκήρεος ἱπποδασείης</tei:l>
					<tei:l n="536">κύμβαχον ἀκρότατον νύξʼ ἔγχεϊ ὀξυόεντι,</tei:l>
					<tei:l n="537">ῥῆξε δʼ ἀφʼ ἵππειον λόφον αὐτοῦ· πᾶς δὲ χαμᾶζε</tei:l>
					<tei:l n="538">κάππεσεν ἐν κονίῃσι νέον φοίνικι φαεινός.</tei:l>
					<tei:l n="539">εἷος ὃ τῷ πολέμιζε μένων, ἔτι δʼ ἔλπετο νίκην,</tei:l>
					<tei:l n="540">τόφρα δέ οἱ Μενέλαος ἀρήϊος ἦλθεν ἀμύντωρ,</tei:l>
					<tei:l n="541">στῆ δʼ εὐρὰξ σὺν δουρὶ λαθών, βάλε δʼ ὦμον ὄπισθεν·</tei:l>
					<tei:l n="542">αἰχμὴ δὲ στέρνοιο διέσσυτο μαιμώωσα</tei:l>
					<tei:l n="543">πρόσσω ἱεμένη· ὃ δʼ ἄρα πρηνὴς ἐλιάσθη.</tei:l>
					<tei:l n="544">τὼ μὲν ἐεισάσθην χαλκήρεα τεύχεʼ ἀπʼ ὤμων</tei:l>
					<tei:l n="545">συλήσειν· Ἕκτωρ δὲ κασιγνήτοισι κέλευσε</tei:l>
					<tei:l n="546">πᾶσι μάλα, πρῶτον δʼ Ἱκεταονίδην ἐνένιπεν</tei:l>
					<tei:l n="547">ἴφθιμον Μελάνιππον. ὃ δʼ ὄφρα μὲν εἰλίποδας βοῦς</tei:l>
					<tei:l n="548">βόσκʼ ἐν Περκώτῃ δηΐων ἀπὸ νόσφιν ἐόντων·</tei:l>
					<tei:l n="549">αὐτὰρ ἐπεὶ Δαναῶν νέες ἤλυθον ἀμφιέλισσαι,</tei:l>
					<tei:l n="550">ἂψ εἰς Ἴλιον ἦλθε, μετέπρεπε δὲ Τρώεσσι,</tei:l>
					<tei:l n="551">ναῖε δὲ πὰρ Πριάμῳ, ὃ δέ μιν τίεν ἶσα τέκεσσι·</tei:l>
					<tei:l n="552">τόν ῥʼ Ἕκτωρ ἐνένιπεν ἔπος τʼ ἔφατʼ ἔκ τʼ ὀνόμαζεν·</tei:l>
					<tei:q>
						<tei:l n="553">οὕτω δὴ Μελάνιππε μεθήσομεν; οὐδέ νυ σοί περ</tei:l>
						<tei:l n="554">ἐντρέπεται φίλον ἦτορ ἀνεψιοῦ κταμένοιο;</tei:l>
						<tei:l n="555">οὐχ ὁράᾳς οἷον Δόλοπος περὶ τεύχεʼ ἕπουσιν;</tei:l>
						<tei:l n="556">ἀλλʼ ἕπευ· οὐ γὰρ ἔτʼ ἔστιν ἀποσταδὸν Ἀργείοισι</tei:l>
						<tei:l n="557">μάρνασθαι, πρίν γʼ ἠὲ κατακτάμεν ἠὲ κατʼ ἄκρης</tei:l>
						<tei:l n="558">Ἴλιον αἰπεινὴν ἑλέειν κτάσθαι τε πολίτας.</tei:l>
						<tei:milestone ed="p" n="559" unit="card"/>
					</tei:q>
					<tei:l n="559">
						<tei:milestone ed="P" unit="para"/>ὣς εἰπὼν ὃ μὲν ἦρχʼ, ὃ δʼ ἅμʼ ἕσπετο ἰσόθεος
						φώς·</tei:l>
					<tei:l n="560">Ἀργείους δʼ ὄτρυνε μέγας Τελαμώνιος Αἴας·</tei:l>
					<tei:q>
						<tei:l n="561">ὦ φίλοι ἀνέρες ἔστε, καὶ αἰδῶ θέσθʼ ἐνὶ θυμῷ,</tei:l>
						<tei:l n="562">ἀλλήλους τʼ αἰδεῖσθε κατὰ κρατερὰς ὑσμίνας.</tei:l>
						<tei:l n="563">αἰδομένων δʼ ἀνδρῶν πλέονες σόοι ἠὲ πέφανται·</tei:l>
						<tei:l n="564">φευγόντων δʼ οὔτʼ ἂρ κλέος ὄρνυται οὔτέ τις ἀλκή.</tei:l>
					</tei:q>
					<tei:l n="565">
						<tei:milestone ed="P" unit="para"/>ὣς ἔφαθʼ, οἳ δὲ καὶ αὐτοὶ ἀλέξασθαι
						μενέαινον,</tei:l>
					<tei:l n="566">ἐν θυμῷ δʼ ἐβάλοντο ἔπος, φράξαντο δὲ νῆας</tei:l>
					<tei:l n="567">ἕρκεϊ χαλκείῳ· ἐπὶ δὲ Ζεὺς Τρῶας ἔγειρεν.</tei:l>
					<tei:l n="568">Ἀντίλοχον δʼ ὄτρυνε βοὴν ἀγαθὸς Μενέλαος·</tei:l>
					<tei:q>
						<tei:l n="569">Ἀντίλοχʼ οὔ τις σεῖο νεώτερος ἄλλος Ἀχαιῶν,</tei:l>
						<tei:l n="570">οὔτε ποσὶν θάσσων οὔτʼ ἄλκιμος ὡς σὺ μάχεσθαι·</tei:l>
						<tei:l n="571">εἴ τινά που Τρώων ἐξάλμενος ἄνδρα βάλοισθα.</tei:l>
					</tei:q>
					<tei:l n="572">
						<tei:milestone ed="P" unit="para"/>ὣς εἰπὼν ὃ μὲν αὖτις ἀπέσσυτο, τὸν δʼ
						ὀρόθυνεν·</tei:l>
					<tei:l n="573">ἐκ δʼ ἔθορε προμάχων, καὶ ἀκόντισε δουρὶ φαεινῷ</tei:l>
					<tei:l n="574">ἀμφὶ ἓ παπτήνας· ὑπὸ δὲ Τρῶες κεκάδοντο</tei:l>
					<tei:l n="575">ἀνδρὸς ἀκοντίσσαντος· ὃ δʼ οὐχ ἅλιον βέλος ἧκεν,</tei:l>
					<tei:l n="576">ἀλλʼ Ἱκετάονος υἱὸν ὑπέρθυμον Μελάνιππον</tei:l>
					<tei:l n="577">νισόμενον πόλεμον δὲ βάλε στῆθος παρὰ μαζόν.</tei:l>
					<tei:l n="578">δούπησεν δὲ πεσών, τὸν δὲ σκότος ὄσσε κάλυψεν.</tei:l>
					<tei:l n="579">Ἀντίλοχος δʼ ἐπόρουσε κύων ὥς, ὅς τʼ ἐπὶ νεβρῷ</tei:l>
					<tei:l n="580">βλημένῳ ἀΐξῃ, τόν τʼ ἐξ εὐνῆφι θορόντα</tei:l>
					<tei:l n="581">θηρητὴρ ἐτύχησε βαλών, ὑπέλυσε δὲ γυῖα·</tei:l>
					<tei:l n="582">ὣς ἐπὶ σοὶ Μελάνιππε θόρʼ Ἀντίλοχος μενεχάρμης</tei:l>
					<tei:l n="583">τεύχεα συλήσων· ἀλλʼ οὐ λάθεν Ἕκτορα δῖον,</tei:l>
					<tei:l n="584">ὅς ῥά οἱ ἀντίος ἦλθε θέων ἀνὰ δηϊοτῆτα.</tei:l>
					<tei:l n="585">Ἀντίλοχος δʼ οὐ μεῖνε θοός περ ἐὼν πολεμιστής,</tei:l>
					<tei:l n="586">ἀλλʼ ὅ γʼ ἄρʼ ἔτρεσε θηρὶ κακὸν ῥέξαντι ἐοικώς,</tei:l>
					<tei:l n="587">ὅς τε κύνα κτείνας ἢ βουκόλον ἀμφὶ βόεσσι</tei:l>
					<tei:l n="588">φεύγει πρίν περ ὅμιλον ἀολλισθήμεναι ἀνδρῶν·</tei:l>
					<tei:l n="589">ὣς τρέσε Νεστορίδης, ἐπὶ δὲ Τρῶές τε καὶ Ἕκτωρ</tei:l>
					<tei:l n="590">ἠχῇ θεσπεσίῃ βέλεα στονόεντα χέοντο·</tei:l>
					<tei:l n="591">στῆ δὲ μεταστρεφθείς, ἐπεὶ ἵκετο ἔθνος ἑταίρων.</tei:l>
				</tei:div>
				</elements>
</citationChunk>
