<?xml version='1.0' encoding='utf-8'?>
<citationChunk xmlns:tei="http://www.tei-c.org/ns/1.0" unit="scene" base_urn="urn:cts:greekLit:tlg0006.tlg014.perseus-grc2" cts_urn="urn:cts:greekLit:tlg0006.tlg014.perseus-grc2:1301-1368" prev_urn="urn:cts:greekLit:tlg0006.tlg014.perseus-grc2:1165-1300" next_urn="urn:cts:greekLit:tlg0006.tlg014.perseus-grc2:1369-1450">
  <elements><tei:div type="choral">
            <tei:div n="1" type="strophe">
               <tei:sp>
                  <tei:speaker>Χορός</tei:speaker>
                  <tei:l rend="indent" n="1301">Ὀρεία ποτὲ δρομάδι κώ-</tei:l>
                  <tei:l n="1302">λῳ μάτηρ θεῶν ἐσύθη ἀνʼ</tei:l>
                  <tei:l n="1303">ὑλάεντα νάπη </tei:l>
                  <tei:l n="1304">ποτάμιόν τε χεῦμʼ ὑδάτων</tei:l>
                  <tei:l n="1305">βαρύβρομόν τε κῦμʼ ἅλιον</tei:l>
                  <tei:l n="1306">πόθῳ τᾶς ἀποιχομένας</tei:l>
                  <tei:l n="1307">ἀρρήτου κούρας.</tei:l>
                  <tei:l n="1308">κρόταλα δὲ βρόμια διαπρύσιον</tei:l>
                  <tei:l n="1309">ἱέντα κέλαδον ἀνεβόα,</tei:l>
                  <tei:l n="1310">θηρῶν ὅτε ζυγίους</tei:l>
                  <tei:l n="1311">ζευξάσᾳ θεᾷ σατίνας</tei:l>
                  <tei:l n="1312">τὰν ἁρπασθεῖσαν κυκλίων</tei:l>
                  <tei:l n="1313">χορῶν ἔξω παρθενίων</tei:l>
                  <tei:l n="1314">μετὰ κούραν, ἀελλόποδες,</tei:l>
                  <tei:l n="1315">ἃ μὲν τόξοις Ἄρτεμις, ἃ δʼ</tei:l>
                  <tei:l n="1316">ἔγχει Γοργῶπις πάνοπλος,</tei:l>
                  <tei:l n="1317">
                     <tei:add>συνείποντο. Ζεὺς δʼ ἑδράνων</tei:add>
                  </tei:l>
                  <tei:l n="1318">αὐγάζων ἐξ οὐρανίων</tei:l>
                  <tei:l n="1318a">ἄλλαν μοῖραν ἔκραινε.</tei:l>
               </tei:sp>
            </tei:div>
            <tei:milestone resp="perseus" unit="card" n="1319"/>
            <tei:div n="1" type="antistrophe">
               <tei:sp>
                  <tei:speaker>Χορός</tei:speaker>
                  <tei:l rend="indent" n="1319">δρομαῖον δʼ ὅτε πολυπλάνη-</tei:l>
                  <tei:l n="1320">τον μάτηρ ἔπαυσε πόνον,</tei:l>
                  <tei:l n="1321">μαστεύουσα <tei:sic>πόνους</tei:sic>
                  </tei:l>
                  <tei:l n="1322">θυγατρὸς ἁρπαγὰς δολίους,</tei:l>
                  <tei:l n="1323">χιονοθρέμμονάς γʼ ἐπέρασʼ</tei:l>
                  <tei:l n="1324">Ἰδαιᾶν Νυμφᾶν σκοπιάς·</tei:l>
                  <tei:l n="1325">ῥίπτει δʼ ἐν πένθει</tei:l>
                  <tei:l n="1326">πέτρινα κατὰ δρία πολυνιφέα· </tei:l>
                  <tei:l n="1327">βροτοῖσι δʼ ἄχλοα πεδία γᾶς</tei:l>
                  <tei:l n="1328">οὐ καρπίζουσʼ ἀρότοις</tei:l>
                  <tei:l n="1329">λαῶν <tei:del>δὲ</tei:del> φθείρει γενεάν·</tei:l>
                  <tei:l n="1330">ποίμναις δʼ οὐχ ἵει θαλερὰς</tei:l>
                  <tei:l n="1331">βοσκὰς εὐφύλλων ἑλίκων,</tei:l>
                  <tei:l n="1332">πόλεων δʼ ἀπέλειπε βίος·</tei:l>
                  <tei:l n="1333">οὐδʼ ἦσαν θεῶν θυσίαι,</tei:l>
                  <tei:l n="1334">βωμοῖς δʼ ἄφλεκτοι πέλανοι·</tei:l>
                  <tei:l n="1335">πηγὰς δʼ ἀμπαύει δροσερὰς</tei:l>
                  <tei:l n="1336">λευκῶν ἐκβάλλειν ὑδάτων</tei:l>
                  <tei:l n="1337">πένθει παιδὸς ἀλάστωρ.</tei:l>
               </tei:sp>
               <tei:milestone resp="perseus" unit="card" n="1338"/>
            </tei:div>
            <tei:div n="2" type="strophe">
               <tei:sp>
                  <tei:speaker>Χορός</tei:speaker>
                  <tei:l rend="indent" n="1338">ἐπεὶ δʼ ἔπαυσʼ εἰλαπίνας</tei:l>
                  <tei:l n="1339">θεοῖς βροτείῳ τε γένει,</tei:l>
                  <tei:l n="1340">Ζεὺς μειλίσσων στυγίους</tei:l>
                  <tei:l n="1341">ματρὸς ὀργὰς ἐνέπει·</tei:l>
                  <tei:l n="1342">βᾶτε, σεμναὶ Χάριτες,</tei:l>
                  <tei:l n="1343">ἴτε, τᾷ περὶ παρθένῳ</tei:l>
                  <tei:l n="1344">Δηοῖ θυμωσαμένᾳ</tei:l>
                  <tei:l n="1344a">λύπαν ἐξαλλάξατʼ ἀλαλᾷ,</tei:l>
                  <tei:l n="1345">Μοῦσαί θʼ ὕμνοισι χορῶν.</tei:l>
                  <tei:l n="1346">χαλκοῦ δʼ αὐδὰν χθονίαν</tei:l>
                  <tei:l n="1347">τύπανά τʼ ἔλαβε βυρσοτενῆ</tei:l>
                  <tei:l n="1348">καλλίστα τότε πρῶτα μακά-</tei:l>
                  <tei:l n="1349">ρων Κύπρις· γέλασέν τε θεὰ </tei:l>
                  <tei:l n="1350">δέξατό τʼ ἐς χέρας</tei:l>
                  <tei:l n="1351">βαρύβρομον αὐλὸν</tei:l>
                  <tei:l n="1352">τερφθεῖσʼ ἀλαλαγμῷ.</tei:l>
               </tei:sp>
            </tei:div>
            <tei:milestone resp="perseus" unit="card" n="1353"/>
            <tei:div n="2" type="antistrophe">
               <tei:sp>
                  <tei:speaker>Χορός</tei:speaker>
                  <tei:l rend="indent" n="1353">ὧν οὐ θέμις <tei:add>σʼ</tei:add> οὔθʼ ὁσία</tei:l>
                  <tei:l n="1354">ʼπʼύρωσας ἐν <tei:add>θεῶν</tei:add> θαλάμοις,</tei:l>
                  <tei:l n="1355">μῆνιν δʼ ἔσχες μεγάλας</tei:l>
                  <tei:l n="1356">ματρός, ὦ παῖ, θυσίας</tei:l>
                  <tei:l n="1357">οὐ σεβίζουσα θεᾶς.</tei:l>
                  <tei:l n="1358">μέγα τοι δύναται νεβρῶν</tei:l>
                  <tei:l n="1359">παμποίκιλοι στολίδες</tei:l>
                  <tei:l n="1360">κισσοῦ τε στεφθεῖσα χλόα</tei:l>
                  <tei:l n="1361">νάρθηκας εἰς ἱερούς,</tei:l>
                  <tei:l n="1362">ῥόμβου θʼ εἱλισσομένα</tei:l>
                  <tei:l n="1363">κύκλιος ἔνοσις αἰθερία,</tei:l>
                  <tei:l n="1364">βακχεύουσά τʼ ἔθειρα Βρομί-</tei:l>
                  <tei:l n="1365">ῳ καὶ παννυχίδες θεᾶς.</tei:l>
                  <tei:l n="1366">
                     <tei:sic>εὖ δέ νιν ἄμασιν</tei:sic>
                  </tei:l>
                  <tei:l n="1367">
                     <tei:sic>ὑπέρβαλε σελάνα</tei:sic>
                  </tei:l>
                  <tei:l n="1368">μορφᾷ μόνον ηὔχεις.</tei:l>
               </tei:sp>
            </tei:div>
         </tei:div>
         </elements>
</citationChunk>
